pptx/__init__.py
pptx/batching.py
pptx/client.py
pptx/commands.py
pptx/decorators.py
pptx/docgen.py
pptx/errors.py
pptx/presentation.py
pptx/shapes.py
pptx/slides.py
pptx/text.py
pptx/typing.py
pptx/units.py
pptx/util.py
pptx/chart/__init__.py
pptx/chart/data.py
pptx/dml/__init__.py
pptx/dml/color.py
pptx/enum/__init__.py
pptx/enum/action.py
pptx/enum/chart.py
pptx/enum/dml.py
pptx/enum/shapes.py
pptx/enum/text.py
athena_python_pptx-0.1.25.dist-info/METADATA
athena_python_pptx-0.1.25.dist-info/WHEEL
athena_python_pptx-0.1.25.dist-info/entry_points.txt
athena_python_pptx-0.1.25.dist-info/RECORD
