Metadata-Version: 2.4
Name: athena-python-pptx
Version: 0.1.25
Summary: Drop-in replacement for python-pptx that connects to PPTX Studio for real-time collaboration
Project-URL: Homepage, https://github.com/pptx-studio/python-sdk
Project-URL: Documentation, https://docs.pptx-studio.com/sdk/python
Project-URL: Repository, https://github.com/pptx-studio/python-sdk
Project-URL: Issues, https://github.com/pptx-studio/python-sdk/issues
Author: PPTX Studio Team
License-Expression: MIT
Keywords: api,powerpoint,pptx,presentation,python-pptx,sdk,slides
Classifier: Development Status :: 3 - Alpha
Classifier: Intended Audience :: Developers
Classifier: License :: OSI Approved :: MIT License
Classifier: Operating System :: OS Independent
Classifier: Programming Language :: Python :: 3
Classifier: Programming Language :: Python :: 3.10
Classifier: Programming Language :: Python :: 3.11
Classifier: Programming Language :: Python :: 3.12
Classifier: Topic :: Office/Business :: Office Suites
Classifier: Topic :: Software Development :: Libraries :: Python Modules
Classifier: Typing :: Typed
Requires-Python: >=3.10
Requires-Dist: requests>=2.28.0
Provides-Extra: dev
Requires-Dist: mypy>=1.0; extra == 'dev'
Requires-Dist: pytest-cov>=4.0; extra == 'dev'
Requires-Dist: pytest>=7.0; extra == 'dev'
Requires-Dist: responses>=0.23; extra == 'dev'
Requires-Dist: ruff>=0.1; extra == 'dev'
Provides-Extra: e2e
Requires-Dist: pytest>=7.0; extra == 'e2e'
Requires-Dist: python-pptx>=0.6.21; extra == 'e2e'
Provides-Extra: visual
Requires-Dist: numpy>=1.24; extra == 'visual'
Requires-Dist: pillow>=10.0; extra == 'visual'
Requires-Dist: pytest>=7.0; extra == 'visual'
Requires-Dist: requests>=2.28.0; extra == 'visual'
